LICENSE
README.rst
setup.py
ROSSpy.egg-info/PKG-INFO
ROSSpy.egg-info/SOURCES.txt
ROSSpy.egg-info/dependency_links.txt
ROSSpy.egg-info/requires.txt
ROSSpy.egg-info/top_level.txt
rosspy/__init__.py
rosspy/ro.py
rosspy/ro_module.json
rosspy/databases/Amm.dat
rosspy/databases/ColdChem.dat
rosspy/databases/Tipping_Hurley.dat
rosspy/databases/core10.dat
rosspy/databases/frezchem.dat
rosspy/databases/iso.dat
rosspy/databases/llnl.dat
rosspy/databases/minteq.dat
rosspy/databases/minteq.v4.dat
rosspy/databases/phreeqc.dat
rosspy/databases/pitzer.dat
rosspy/databases/sit.dat
rosspy/databases/wateq4f.dat
rosspy/processed_databases/Amm.json
rosspy/processed_databases/ColdChem.json
rosspy/processed_databases/Tipping_Hurley.json
rosspy/processed_databases/core10.json
rosspy/processed_databases/frezchem.json
rosspy/processed_databases/iso.json
rosspy/processed_databases/llnl.json
rosspy/processed_databases/minteq.json
rosspy/processed_databases/minteq.v4.json
rosspy/processed_databases/phreeqc.json
rosspy/processed_databases/pitzer.json
rosspy/processed_databases/sit.json
rosspy/processed_databases/wateq4f.json
rosspy/test/2020-09-03_APF_Palo Duro Basin-BW30-400_PE=100%_1.1.pqi
rosspy/test/test_ro.py
rosspy/test/test_ro_unix.py
rosspy/test/__pycache__/test_core.cpython-38-pytest-6.0.1.pyc
rosspy/test/__pycache__/test_ro.cpython-38-pytest-6.0.1.pyc
rosspy/water_bodies/bakken_formation.json
rosspy/water_bodies/marcellus_appalachian_basin.json
rosspy/water_bodies/mediterranean_sea.json
rosspy/water_bodies/michigan_basin.json
rosspy/water_bodies/north_german_basin.json
rosspy/water_bodies/palo_duro_basin.json
rosspy/water_bodies/red_sea.json
rosspy/water_bodies/western_pennsylvania_basin.json