Metadata-Version: 2.1
Name: ROSSpy
Version: 0.1.6
Summary: Software for predicting the brine concentrations and scaling quantities after RO desalination.
Home-page: https://github.com/freiburgermsu/ROSSpy
Author: Andrew Freiburger
Author-email: andrewfreiburger@gmail.com
License: MIT License
Project-URL: Documentation, https://rosspy.readthedocs.io/en/latest/index.html
Project-URL: Issues, https://github.com/freiburgermsu/ROSSpy/issues
Keywords: desalination,reactive transport,geochemistry,sustainability,civil engineering,fluid mechanics
Platform: UNKNOWN
License-File: LICENSE
